hcsr04sensor/__init__.py
hcsr04sensor/sensor.py
hcsr04sensor-1.7.data/scripts/hcsr04.py
hcsr04sensor-1.7.dist-info/LICENSE
hcsr04sensor-1.7.dist-info/METADATA
hcsr04sensor-1.7.dist-info/WHEEL
hcsr04sensor-1.7.dist-info/top_level.txt
hcsr04sensor-1.7.dist-info/RECORD
