Metadata-Version: 2.1
Name: hcsr04sensor
Version: 1.7
Summary: Module to access the HCSR04 sensor on a Raspberry Pi
Home-page: https://www.linuxnorth.org/hcsr04sensor/
Download-URL: https://github.com/alaudet/hcsr04sensor/releases
Author: Al Audet
Author-email: alaudet@linuxnorth.org
License: MIT License
Classifier: Development Status :: 5 - Production/Stable
Classifier: Environment :: Console
Classifier: Intended Audience :: End Users/Desktop
Classifier: Natural Language :: English
Classifier: Operating System :: POSIX :: Linux
Classifier: Programming Language :: Python :: 3.7
Classifier: Programming Language :: Python :: 3.9
Classifier: Topic :: Home Automation
Classifier: License :: OSI Approved :: MIT License
License-File: LICENSE
